MANIFEST.in
README.rst
setup.py
getmovie/__init__.py
getmovie/__main__.py
getmovie/getmovie.py
getmovie.egg-info/PKG-INFO
getmovie.egg-info/SOURCES.txt
getmovie.egg-info/dependency_links.txt
getmovie.egg-info/entry_points.txt
getmovie.egg-info/requires.txt
getmovie.egg-info/top_level.txt