Metadata-Version: 1.1
Name: getmovie
Version: 1.0.1
Summary: Look up movie from YTS
Home-page: https://github.com/blha303/getmovie/
Author: Steven Smith
Author-email: stevensmith.ome@gmail.com
License: MIT
Platform: UNKNOWN
Classifier: Development Status :: 4 - Beta
Classifier: License :: OSI Approved :: MIT License
Classifier: Programming Language :: Python :: 3.4
Classifier: Programming Language :: Python :: 3
Classifier: Intended Audience :: End Users/Desktop
Classifier: Intended Audience :: System Administrators
Classifier: Topic :: Multimedia :: Sound/Audio
